xiaopy/__init__.py
xiaopy/xiaopy.py
PyGameAutoAndroid-0.0.22.dist-info/METADATA
PyGameAutoAndroid-0.0.22.dist-info/WHEEL
PyGameAutoAndroid-0.0.22.dist-info/top_level.txt
PyGameAutoAndroid-0.0.22.dist-info/RECORD
