Metadata-Version: 2.1
Name: PyGameAutoAndroid
Version: 0.0.22
Summary: 小派精灵手机自动化
Author: 小派精灵
Author-email: 3383716176@qq.com
License: MIT
Classifier: Programming Language :: Python :: 3
Classifier: License :: OSI Approved :: MIT License
